usexif/__init__.py
usexif/date.py
usexif/geo.py
usexif-1.0.3.dist-info/DESCRIPTION.rst
usexif-1.0.3.dist-info/METADATA
usexif-1.0.3.dist-info/RECORD
usexif-1.0.3.dist-info/WHEEL
usexif-1.0.3.dist-info/metadata.json
usexif-1.0.3.dist-info/top_level.txt
