Metadata-Version: 2.0
Name: usexif
Version: 1.0.3
Summary: get geo data and taken date
Home-page: https://github.com/zironycho/usexif
Author: Juncheol Cho
Author-email: zironycho@gmail.com
License: MIT
Download-URL: https://github.com/zironycho/usexif/tarball/1.0.3
Keywords: exif,geo,taken,geo,geographic coordinate,coordinate
Platform: UNKNOWN
Requires-Dist: exifread
